EBNFParser-2.1.3.dist-info/DESCRIPTION.rst
EBNFParser-2.1.3.dist-info/METADATA
EBNFParser-2.1.3.dist-info/RECORD
EBNFParser-2.1.3.dist-info/WHEEL
EBNFParser-2.1.3.dist-info/entry_points.txt
EBNFParser-2.1.3.dist-info/metadata.json
EBNFParser-2.1.3.dist-info/top_level.txt
Ruikowa/Command.py
Ruikowa/Config.py
Ruikowa/ErrorFamily.py
Ruikowa/ErrorHandler.py
Ruikowa/__init__.py
Ruikowa/color.py
Ruikowa/io.py
Ruikowa/Bootstrap/Ast.py
Ruikowa/Bootstrap/Compile.py
Ruikowa/Bootstrap/Parser.py
Ruikowa/Bootstrap/Token.py
Ruikowa/Bootstrap/__init__.py
Ruikowa/Core/BaseDef.py
Ruikowa/Core/__init__.py
Ruikowa/ObjectRegex/ASTDef.py
Ruikowa/ObjectRegex/MetaInfo.py
Ruikowa/ObjectRegex/Node.py
Ruikowa/ObjectRegex/Optimize.py
Ruikowa/ObjectRegex/Tokenizer.py
Ruikowa/ObjectRegex/__init__.py
Ruikowa/Tools/__init__.py
