Metadata-Version: 2.0
Name: EBNFParser
Version: 2.1.3
Summary: very powerful and optional parser framework for python
Home-page: https://github.com/thautwarm/EBNFParser
Author: thautwarm
Author-email: twshere@outlook.com
License: MIT
Keywords: parser,parser framework,parser generator,gramamr,ast,tokenizer,EBNF,BNF
Platform: any
Classifier: Programming Language :: Python :: 3.6
Classifier: Programming Language :: Python :: 3.7
Classifier: Programming Language :: Python :: Implementation :: CPython
Requires-Dist: Linq (==0.3.1)
